Workbook

Sheet Dashboard
B2: Avg Leverage Ratio | C2: Avg ROA | D2: Total Assets | E2: Number of Banks over 10x Leveraged
B3: =_xlfn.AGGREGATE(1,6,dashboard_data_raw!M2:M261) -> 9.5979049 | C3: =_xlfn.AGGREGATE(1,6,dashboard_data_raw!N2:N261) -> 0.0095468342 | D3: =_xlfn.AGGREGATE(9,6,dashboard_data_raw!F2:F261) -> 21171198608467 | E3: =COUNTIF(dashboard_data_raw!$M$2:$M$261,">10") -> 90
A5: "Size Tier Filter:" | B5: Small
A6: Avg Leverage Ratio | B6: {=SUMPRODUCT((dashboard_data_raw!$O$2:$O$261=$B$5)*IFERROR(dashboard_data_raw!$M$2:$M$261,0)) / SUMPRODUCT((dashboard_data_raw!$O$2:$O$261=$B$5)*ISNUMBER(dashboard_data_raw!$M$2:$M$261))} -> 10.783984
A7: Avg ROA | B7: {=SUMPRODUCT((dashboard_data_raw!$O$2:$O$261=$B$5)*IFERROR(dashboard_data_raw!$N$2:$N$261,0)) / SUMPRODUCT((dashboard_data_raw!$O$2:$O$261=$B$5)*ISNUMBER(dashboard_data_raw!$M$2:$M$261))} -> 0.0084321466
A8: Number of Banks | B8: =COUNTIFS(dashboard_data_raw!$O$2:$O$261,$B$5) -> 65

Sheet State_v_National
C1: Total Assets | D1: Total Liabilities | E1: Total Net Worth | F1: Avg EPS
A2: State Commercial Banks | B2: 6022 | C2: =SUMIF(dashboard_data_raw!B2:B261, B2, dashboard_data_raw!F2:F261) -> 3936318289521 | D2: =SUMIF(dashboard_data_raw!B2:B261, B2, dashboard_data_raw!I2:I261) -> 3518135159589 | E2: =C2-D2 -> 418183129932 | F2: =AVERAGEIF(dashboard_data_raw!B2:B261, B2, dashboard_data_raw!G2:G261) -> 4.1703409
A3: National Commerical Banks | B3: 6021 | C3: =SUMIF(dashboard_data_raw!B3:B262, B3, dashboard_data_raw!F3:F262) -> 17234880318946 | D3: =SUMIF(dashboard_data_raw!B3:B262, B3, dashboard_data_raw!I3:I262) -> 15637356524968 | E3: =C3-D3 -> 1597523793978 | F3: =AVERAGEIF(dashboard_data_raw!B3:B262, B3, dashboard_data_raw!G3:G262) -> 5.3752439

Sheet dashboard_data_raw
A1: Number | B1: SIC | C1: Name | D1: CIK | E1: adsh | F1: Assets | G1: EPS | H1: Interest | I1: Liabilities | J1: Net Worth | K1: NetIncomeLoss | L1: StockholdersEquity | M1: Leverage Ratio | N1: ROA | O1: Size Tier | P1: Q1 Breakpoint | Q1: Q3 Breakpoint | R1: Bank | S1: Net Income Loss | T1: Rank
A2: 1 | B2: {=_xlfn.XLOOKUP(companies[adsh], companies[adsh], companies[sic])} -> 6022 | C2: {=_xlfn.XLOOKUP(companies[adsh], companies[adsh], companies[name])} -> INDEPENDENT BANK CORP /MI/ | D2: {=_xlfn.XLOOKUP(companies[adsh], companies[adsh], companies[cik])} -> 39311 | E2: {=_xlfn.XLOOKUP(companies[adsh], companies[adsh], companies[adsh])} -> 0000039311-26-000009 | F2: =IFERROR(GETPIVOTDATA("value", financials_wide!$A$3, "adsh", $E2, "tag", "Assets"),"") -> 5505720000 | G2: =IFERROR(GETPIVOTDATA("value", financials_wide!$A$3, "adsh", $E2, "tag", "EarningsPerShareBasic"),"") -> 3.3 | H2: =IFERROR(IFERROR(GETPIVOTDATA("value", financials_wide!$A$3, "adsh", $E2, "tag", "InterestAndDividendIncomeOperating"), GETPIVOTDATA("value", financials_wide!$A$3, "adsh", $E2, "tag", "InterestIncomeOperating")),"") -> 269737000 | I2: =IFERROR(GETPIVOTDATA("value", financials_wide!$A$3, "adsh", $E2, "tag", "Liabilities"),"") -> 5002769000 | J2: =IFERROR(F2-I2,"") -> 502951000 | K2: =IFERROR(GETPIVOTDATA("value", financials_wide!$A$3, "adsh", $E2, "tag", "NetIncomeLoss"),"") -> 68541000 | L2: =IFERROR(GETPIVOTDATA("value", financials_wide!$A$3, "adsh", $E2, "tag", "StockholdersEquity"),"") -> 502951000 | M2: =IFERROR(F2/L2,NA()) -> 10.946832 | N2: =IFERROR(K2/F2,NA()) -> 0.012449053 | O2: =IF(F2="","",IF(F2<=$P$2,"Small",IF(F2<=$Q$2,"Mid","Large"))) -> Mid | P2: =_xlfn.QUARTILE.INC(F2:F261,1) -> 2652513750 | Q2: =_xlfn.QUARTILE.INC(F2:F261,3) -> 19369930250 | R2: =INDEX($C$2:$C$261,MATCH(S2,$K$2:$K$261,0)) -> JPMORGAN CHASE & CO | S2: =LARGE($K$2:$K$261,ROW()-1) -> 57048000000 | T2: 1
A3: 2 | B3: 6022 | C3: HORIZON BANCORP INC /IN/ | D3: 706129 | E3: 0000706129-26-000024 | F3: =IFERROR(GETPIVOTDATA("value", financials_wide!$A$3, "adsh", $E3, "tag", "Assets"),"") -> 6436611000 | G3: =IFERROR(GETPIVOTDATA("value", financials_wide!$A$3, "adsh", $E3, "tag", "EarningsPerShareBasic"),"") -> -3.24 | H3: =IFERROR(IFERROR(GETPIVOTDATA("value", financials_wide!$A$3, "adsh", $E3, "tag", "InterestAndDividendIncomeOperating"), GETPIVOTDATA("value", financials_wide!$A$3, "adsh", $E3, "tag", "InterestIncomeOperating")),"") -> 362777000 | I3: =IFERROR(GETPIVOTDATA("value", financials_wide!$A$3, "adsh", $E3, "tag", "Liabilities"),"") -> 5748360000 | J3: =IFERROR(F3-I3,"") -> 688251000 | K3: =IFERROR(GETPIVOTDATA("value", financials_wide!$A$3, "adsh", $E3, "tag", "NetIncomeLoss"),"") -> -150482000 | L3: =IFERROR(GETPIVOTDATA("value", financials_wide!$A$3, "adsh", $E3, "tag", "StockholdersEquity"),"") -> 688251000 | M3: =IFERROR(F3/L3,NA()) -> 9.3521273 | N3: =IFERROR(K3/F3,NA()) -> -0.023379073 | O3: =IF(F3="","",IF(F3<=$P$2,"Small",IF(F3<=$Q$2,"Mid","Large"))) -> Mid | R3: =INDEX($C$2:$C$261,MATCH(S3,$K$2:$K$261,0)) -> BANK OF AMERICA CORP /DE/ | S3: =LARGE($K$2:$K$261,ROW()-1) -> 30509000000 | T3: 2
A4: 3 | B4: 6022 | C4: UNION BANKSHARES INC | D4: 706863 | E4: 0000706863-26-000029 | F4: =IFERROR(GETPIVOTDATA("value", financials_wide!$A$3, "adsh", $E4, "tag", "Assets"),"") -> 1617191000 | G4: =IFERROR(GETPIVOTDATA("value", financials_wide!$A$3, "adsh", $E4, "tag", "EarningsPerShareBasic"),"") -> 2.43 | H4: =IFERROR(IFERROR(GETPIVOTDATA("value", financials_wide!$A$3, "adsh", $E4, "tag", "InterestAndDividendIncomeOperating"), GETPIVOTDATA("value", financials_wide!$A$3, "adsh", $E4, "tag", "InterestIncomeOperating")),"") -> 75788000 | I4: =IFERROR(GETPIVOTDATA("value", financials_wide!$A$3, "adsh", $E4, "tag", "Liabilities"),"") -> 1536327000 | J4: =IFERROR(F4-I4,"") -> 80864000 | K4: =IFERROR(GETPIVOTDATA("value", financials_wide!$A$3, "adsh", $E4, "tag", "NetIncomeLoss"),"") -> 11080000 | L4: =IFERROR(GETPIVOTDATA("value", financials_wide!$A$3, "adsh", $E4, "tag", "StockholdersEquity"),"") -> 80864000 | M4: =IFERROR(F4/L4,NA()) -> 19.998899 | N4: =IFERROR(K4/F4,NA()) -> 0.0068513861 | O4: =IF(F4="","",IF(F4<=$P$2,"Small",IF(F4<=$Q$2,"Mid","Large"))) -> Small | R4: =INDEX($C$2:$C$261,MATCH(S4,$K$2:$K$261,0)) -> WELLS FARGO & COMPANY/MN | S4: =LARGE($K$2:$K$261,ROW()-1) -> 21338000000 | T4: 3
A5: 4 | B5: 6022 | C5: COLONY BANKCORP INC | D5: 711669 | E5: 0000711669-26-000007 | F5: =IFERROR(GETPIVOTDATA("value", financials_wide!$A$3, "adsh", $E5, "tag", "Assets"),"") -> 3735401000 | G5: =IFERROR(GETPIVOTDATA("value", financials_wide!$A$3, "adsh", $E5, "tag", "EarningsPerShareBasic"),"") -> 1.59 | H5: =IFERROR(IFERROR(GETPIVOTDATA("value", financials_wide!$A$3, "adsh", $E5, "tag", "InterestAndDividendIncomeOperating"), GETPIVOTDATA("value", financials_wide!$A$3, "adsh", $E5, "tag", "InterestIncomeOperating")),"") -> 149952000 | I5: =IFERROR(GETPIVOTDATA("value", financials_wide!$A$3, "adsh", $E5, "tag", "Liabilities"),"") -> 3359481000 | J5: =IFERROR(F5-I5,"") -> 375920000 | K5: =IFERROR(GETPIVOTDATA("value", financials_wide!$A$3, "adsh", $E5, "tag", "NetIncomeLoss"),"") -> 28253000 | L5: =IFERROR(GETPIVOTDATA("value", financials_wide!$A$3, "adsh", $E5, "tag", "StockholdersEquity"),"") -> 375920000 | M5: =IFERROR(F5/L5,NA()) -> 9.9366913 | N5: =IFERROR(K5/F5,NA()) -> 0.0075635789 | O5: =IF(F5="","",IF(F5<=$P$2,"Small",IF(F5<=$Q$2,"Mid","Large"))) -> Mid | R5: =INDEX($C$2:$C$261,MATCH(S5,$K$2:$K$261,0)) -> CITIGROUP INC | S5: =LARGE($K$2:$K$261,ROW()-1) -> 14306000000 | T5: 4
A6: 5 | B6: 6022 | C6: FIRST FINANCIAL CORP /IN/ | D6: 714562 | E6: 0000714562-26-000014 | F6: =IFERROR(GETPIVOTDATA("value", financials_wide!$A$3, "adsh", $E6, "tag", "Assets"),"") -> 5756126000 | G6: =IFERROR(GETPIVOTDATA("value", financials_wide!$A$3, "adsh", $E6, "tag", "EarningsPerShareBasic"),"") -> 6.68 | H6: =IFERROR(IFERROR(GETPIVOTDATA("value", financials_wide!$A$3, "adsh", $E6, "tag", "InterestAndDividendIncomeOperating"), GETPIVOTDATA("value", financials_wide!$A$3, "adsh", $E6, "tag", "InterestIncomeOperating")),"") -> 305588000 | I6: =IFERROR(GETPIVOTDATA("value", financials_wide!$A$3, "adsh", $E6, "tag", "Liabilities"),"") -> 5105257000 | J6: =IFERROR(F6-I6,"") -> 650869000 | K6: =IFERROR(GETPIVOTDATA("value", financials_wide!$A$3, "adsh", $E6, "tag", "NetIncomeLoss"),"") -> 79208000 | L6: =IFERROR(GETPIVOTDATA("value", financials_wide!$A$3, "adsh", $E6, "tag", "StockholdersEquity"),"") -> 650869000 | M6: =IFERROR(F6/L6,NA()) -> 8.843755 | N6: =IFERROR(K6/F6,NA()) -> 0.013760644 | O6: =IF(F6="","",IF(F6<=$P$2,"Small",IF(F6<=$Q$2,"Mid","Large"))) -> Mid | R6: =INDEX($C$2:$C$261,MATCH(S6,$K$2:$K$261,0)) -> US BANCORP DE | S6: =LARGE($K$2:$K$261,ROW()-1) -> 7570000000 | T6: 5
A7: 6 | B7: 6021 | C7: ARROW FINANCIAL CORP | D7: 717538 | E7: 0000717538-26-000037 | F7: =IFERROR(GETPIVOTDATA("value", financials_wide!$A$3, "adsh", $E7, "tag", "Assets"),"") -> 4445862000 | G7: =IFERROR(GETPIVOTDATA("value", financials_wide!$A$3, "adsh", $E7, "tag", "EarningsPerShareBasic"),"") -> 2.65 | H7: =IFERROR(IFERROR(GETPIVOTDATA("value", financials_wide!$A$3, "adsh", $E7, "tag", "InterestAndDividendIncomeOperating"), GETPIVOTDATA("value", financials_wide!$A$3, "adsh", $E7, "tag", "InterestIncomeOperating")),"") -> 0 | I7: =IFERROR(GETPIVOTDATA("value", financials_wide!$A$3, "adsh", $E7, "tag", "Liabilities"),"") -> 4014010000 | J7: =IFERROR(F7-I7,"") -> 431852000 | K7: =IFERROR(GETPIVOTDATA("value", financials_wide!$A$3, "adsh", $E7, "tag", "NetIncomeLoss"),"") -> 43953000 | L7: =IFERROR(GETPIVOTDATA("value", financials_wide!$A$3, "adsh", $E7, "tag", "StockholdersEquity"),"") -> 431852000 | M7: =IFERROR(F7/L7,NA()) -> 10.294874 | N7: =IFERROR(K7/F7,NA()) -> 0.0098862718 | O7: =IF(F7="","",IF(F7<=$P$2,"Small",IF(F7<=$Q$2,"Mid","Large"))) -> Mid | R7: =INDEX($C$2:$C$261,MATCH(S7,$K$2:$K$261,0)) -> BANK OF NEW YORK MELLON CORP | S7: =LARGE($K$2:$K$261,ROW()-1) -> 5549000000 | T7: 6
A8: 7 | B8: 6022 | C8: FRANKLIN FINANCIAL SERVICES CORP /PA/ | D8: 723646 | E8: 0000723646-26-000016 | F8: =IFERROR(GETPIVOTDATA("value", financials_wide!$A$3, "adsh", $E8, "tag", "Assets"),"") -> 2239018000 | G8: =IFERROR(GETPIVOTDATA("value", financials_wide!$A$3, "adsh", $E8, "tag", "EarningsPerShareBasic"),"") -> 4.76 | H8: =IFERROR(IFERROR(GETPIVOTDATA("value", financials_wide!$A$3, "adsh", $E8, "tag", "InterestAndDividendIncomeOperating"), GETPIVOTDATA("value", financials_wide!$A$3, "adsh", $E8, "tag", "InterestIncomeOperating")),"") -> 114371000 | I8: =IFERROR(GETPIVOTDATA("value", financials_wide!$A$3, "adsh", $E8, "tag", "Liabilities"),"") -> 2063776000 | J8: =IFERROR(F8-I8,"") -> 175242000 | K8: =IFERROR(GETPIVOTDATA("value", financials_wide!$A$3, "adsh", $E8, "tag", "NetIncomeLoss"),"") -> 21226000 | L8: =IFERROR(GETPIVOTDATA("value", financials_wide!$A$3, "adsh", $E8, "tag", "StockholdersEquity"),"") -> 175242000 | M8: =IFERROR(F8/L8,NA()) -> 12.77672 | N8: =IFERROR(K8/F8,NA()) -> 0.0094800488 | O8: =IF(F8="","",IF(F8<=$P$2,"Small",IF(F8<=$Q$2,"Mid","Large"))) -> Small | R8: =INDEX($C$2:$C$261,MATCH(S8,$K$2:$K$261,0)) -> STATE STREET CORP | S8: =LARGE($K$2:$K$261,ROW()-1) -> 2945000000 | T8: 7
A9: 8 | B9: 6022 | C9: HILLS BANCORPORATION | D9: 732417 | E9: 0000732417-26-000022 | F9: =IFERROR(GETPIVOTDATA("value", financials_wide!$A$3, "adsh", $E9, "tag", "Assets"),"") -> 4647870000 | G9: =IFERROR(GETPIVOTDATA("value", financials_wide!$A$3, "adsh", $E9, "tag", "EarningsPerShareBasic"),"") -> 6.82 | H9: =IFERROR(IFERROR(GETPIVOTDATA("value", financials_wide!$A$3, "adsh", $E9, "tag", "InterestAndDividendIncomeOperating"), GETPIVOTDATA("value", financials_wide!$A$3, "adsh", $E9, "tag", "InterestIncomeOperating")),"") -> 0 | I9: =IFERROR(GETPIVOTDATA("value", financials_wide!$A$3, "adsh", $E9, "tag", "Liabilities"),"") -> 4045161000 | J9: =IFERROR(F9-I9,"") -> 602709000 | K9: =IFERROR(GETPIVOTDATA("value", financials_wide!$A$3, "adsh", $E9, "tag", "NetIncomeLoss"),"") -> 60502000 | L9: =IFERROR(GETPIVOTDATA("value", financials_wide!$A$3, "adsh", $E9, "tag", "StockholdersEquity"),"") -> 548234000 | M9: =IFERROR(F9/L9,NA()) -> 8.4778945 | N9: =IFERROR(K9/F9,NA()) -> 0.013017145 | O9: =IF(F9="","",IF(F9<=$P$2,"Small",IF(F9<=$Q$2,"Mid","Large"))) -> Mid | R9: =INDEX($C$2:$C$261,MATCH(S9,$K$2:$K$261,0)) -> M&T BANK CORP | S9: =LARGE($K$2:$K$261,ROW()-1) -> 2851000000 | T9: 8
A10: 9 | B10: 6022 | C10: CNB FINANCIAL CORP/PA | D10: 736772 | E10: 0000736772-26-000031 | F10: =IFERROR(GETPIVOTDATA("value", financials_wide!$A$3, "adsh", $E10, "tag", "Assets"),"") -> 8396435000 | G10: =IFERROR(GETPIVOTDATA("value", financials_wide!$A$3, "adsh", $E10, "tag", "EarningsPerShareBasic"),"") -> 2.5 | H10: =IFERROR(IFERROR(GETPIVOTDATA("value", financials_wide!$A$3, "adsh", $E10, "tag", "InterestAndDividendIncomeOperating"), GETPIVOTDATA("value", financials_wide!$A$3, "adsh", $E10, "tag", "InterestIncomeOperating")),"") -> 392345000 | I10: =IFERROR(GETPIVOTDATA("value", financials_wide!$A$3, "adsh", $E10, "tag", "Liabilities"),"") -> 7524308000 | J10: =IFERROR(F10-I10,"") -> 872127000 | K10: =IFERROR(GETPIVOTDATA("value", financials_wide!$A$3, "adsh", $E10, "tag", "NetIncomeLoss"),"") -> 66131000 | L10: =IFERROR(GETPIVOTDATA("value", financials_wide!$A$3, "adsh", $E10, "tag", "StockholdersEquity"),"") -> 872127000 | M10: =IFERROR(F10/L10,NA()) -> 9.627537 | N10: =IFERROR(K10/F10,NA()) -> 0.0078760807 | O10: =IF(F10="","",IF(F10<=$P$2,"Small",IF(F10<=$Q$2,"Mid","Large"))) -> Mid | R10: =INDEX($C$2:$C$261,MATCH(S10,$K$2:$K$261,0)) -> FIFTH THIRD BANCORP | S10: =LARGE($K$2:$K$261,ROW()-1) -> 2522000000 | T10: 9
A11: 10 | B11: 6022 | C11: FIRST KEYSTONE CORP | D11: 737875 | E11: 0000737875-26-000009 | F11: =IFERROR(GETPIVOTDATA("value", financials_wide!$A$3, "adsh", $E11, "tag", "Assets"),"") -> 1530977000 | G11: =IFERROR(GETPIVOTDATA("value", financials_wide!$A$3, "adsh", $E11, "tag", "EarningsPerShareBasic"),"") -> 0.99 | H11: =IFERROR(IFERROR(GETPIVOTDATA("value", financials_wide!$A$3, "adsh", $E11, "tag", "InterestAndDividendIncomeOperating"), GETPIVOTDATA("value", financials_wide!$A$3, "adsh", $E11, "tag", "InterestIncomeOperating")),"") -> 77199000 | I11: =IFERROR(GETPIVOTDATA("value", financials_wide!$A$3, "adsh", $E11, "tag", "Liabilities"),"") -> 1417917000 | J11: =IFERROR(F11-I11,"") -> 113060000 | K11: =IFERROR(GETPIVOTDATA("value", financials_wide!$A$3, "adsh", $E11, "tag", "NetIncomeLoss"),"") -> 6152000 | L11: =IFERROR(GETPIVOTDATA("value", financials_wide!$A$3, "adsh", $E11, "tag", "StockholdersEquity"),"") -> 113060000 | M11: =IFERROR(F11/L11,NA()) -> 13.541279 | N11: =IFERROR(K11/F11,NA()) -> 0.0040183491 | O11: =IF(F11="","",IF(F11<=$P$2,"Small",IF(F11<=$Q$2,"Mid","Large"))) -> Small | R11: =INDEX($C$2:$C$261,MATCH(S11,$K$2:$K$261,0)) -> CAPITAL ONE FINANCIAL CORP | S11: =LARGE($K$2:$K$261,ROW()-1) -> 2453000000 | T11: 10
A12: 11 | B12: 6021 | C12: CAMDEN NATIONAL CORP | D12: 750686 | E12: 0000750686-26-000010 | F12: =IFERROR(GETPIVOTDATA("value", financials_wide!$A$3, "adsh", $E12, "tag", "Assets"),"") -> 6974584000 | G12: =IFERROR(GETPIVOTDATA("value", financials_wide!$A$3, "adsh", $E12, "tag", "EarningsPerShareBasic"),"") -> 3.86 | H12: =IFERROR(IFERROR(GETPIVOTDATA("value", financials_wide!$A$3, "adsh", $E12, "tag", "InterestAndDividendIncomeOperating"), GETPIVOTDATA("value", financials_wide!$A$3, "adsh", $E12, "tag", "InterestIncomeOperating")),"") -> 320655000 | I12: =IFERROR(GETPIVOTDATA("value", financials_wide!$A$3, "adsh", $E12, "tag", "Liabilities"),"") -> 6278026000 | J12: =IFERROR(F12-I12,"") -> 696558000 | K12: =IFERROR(GETPIVOTDATA("value", financials_wide!$A$3, "adsh", $E12, "tag", "NetIncomeLoss"),"") -> 65160000 | L12: =IFERROR(GETPIVOTDATA("value", financials_wide!$A$3, "adsh", $E12, "tag", "StockholdersEquity"),"") -> 696558000 | M12: =IFERROR(F12/L12,NA()) -> 10.012926 | N12: =IFERROR(K12/F12,NA()) -> 0.0093424927 | O12: =IF(F12="","",IF(F12<=$P$2,"Small",IF(F12<=$Q$2,"Mid","Large"))) -> Mid | R12: =INDEX($C$2:$C$261,MATCH(S12,$K$2:$K$261,0)) -> HUNTINGTON BANCSHARES INC /MD/ | S12: =LARGE($K$2:$K$261,ROW()-1) -> 2211000000 | T12: 11
A13: 12 | B13: 6021 | C13: FIRST BANCORP, INC /ME/ | D13: 765207 | E13: 0000765207-26-000067 | F13: =IFERROR(GETPIVOTDATA("value", financials_wide!$A$3, "adsh", $E13, "tag", "Assets"),"") -> 3166303000 | G13: =IFERROR(GETPIVOTDATA("value", financials_wide!$A$3, "adsh", $E13, "tag", "EarningsPerShareBasic"),"") -> 3.1 | H13: =IFERROR(IFERROR(GETPIVOTDATA("value", financials_wide!$A$3, "adsh", $E13, "tag", "InterestAndDividendIncomeOperating"), GETPIVOTDATA("value", financials_wide!$A$3, "adsh", $E13, "tag", "InterestIncomeOperating")),"") -> 160271000 | I13: =IFERROR(GETPIVOTDATA("value", financials_wide!$A$3, "adsh", $E13, "tag", "Liabilities"),"") -> 2883160000 | J13: =IFERROR(F13-I13,"") -> 283143000 | K13: =IFERROR(GETPIVOTDATA("value", financials_wide!$A$3, "adsh", $E13, "tag", "NetIncomeLoss"),"") -> 34394000 | L13: =IFERROR(GETPIVOTDATA("value", financials_wide!$A$3, "adsh", $E13, "tag", "StockholdersEquity"),"") -> 283143000 | M13: =IFERROR(F13/L13,NA()) -> 11.182699 | N13: =IFERROR(K13/F13,NA()) -> 0.010862511 | O13: =IF(F13="","",IF(F13<=$P$2,"Small",IF(F13<=$Q$2,"Mid","Large"))) -> Mid | R13: =INDEX($C$2:$C$261,MATCH(S13,$K$2:$K$261,0)) -> FIRST CITIZENS BANCSHARES INC /DE/ | S13: =LARGE($K$2:$K$261,ROW()-1) -> 2206000000 | T13: 12
A14: 13 | B14: 6022 | C14: HBT FINANCIAL, INC. | D14: 775215 | E14: 0000775215-26-000025 | F14: =IFERROR(GETPIVOTDATA("value", financials_wide!$A$3, "adsh", $E14, "tag", "Assets"),"") -> 5071390000 | G14: =IFERROR(GETPIVOTDATA("value", financials_wide!$A$3, "adsh", $E14, "tag", "EarningsPerShareBasic"),"") -> 2.44 | H14: =IFERROR(IFERROR(GETPIVOTDATA("value", financials_wide!$A$3, "adsh", $E14, "tag", "InterestAndDividendIncomeOperating"), GETPIVOTDATA("value", financials_wide!$A$3, "adsh", $E14, "tag", "InterestIncomeOperating")),"") -> 255784000 | I14: =IFERROR(GETPIVOTDATA("value", financials_wide!$A$3, "adsh", $E14, "tag", "Liabilities"),"") -> 4455892000 | J14: =IFERROR(F14-I14,"") -> 615498000 | K14: =IFERROR(GETPIVOTDATA("value", financials_wide!$A$3, "adsh", $E14, "tag", "NetIncomeLoss"),"") -> 77008000 | L14: =IFERROR(GETPIVOTDATA("value", financials_wide!$A$3, "adsh", $E14, "tag", "StockholdersEquity"),"") -> 615498000 | M14: =IFERROR(F14/L14,NA()) -> 8.2394906 | N14: =IFERROR(K14/F14,NA()) -> 0.015184792 | O14: =IF(F14="","",IF(F14<=$P$2,"Small",IF(F14<=$Q$2,"Mid","Large"))) -> Mid | R14: =INDEX($C$2:$C$261,MATCH(S14,$K$2:$K$261,0)) -> REGIONS FINANCIAL CORP | S14: =LARGE($K$2:$K$261,ROW()-1) -> 2156000000 | T14: 13
... A16: 15 | B16: 6022 | C16: MID PENN BANCORP INC | D16: 879635 | E16: 0000879635-26-000026 | F16: =IFERROR(GETPIVOTDATA("value", financials_wide!$A$3, "adsh", $E16, "tag", "Assets"),"") -> 6133896000 | G16: =IFERROR(GETPIVOTDATA("value", financials_wide!$A$3, "adsh", $E16, "tag", "EarningsPerShareBasic"),"") -> 2.59 | H16: =IFERROR(IFERROR(GETPIVOTDATA("value", financials_wide!$A$3, "adsh", $E16, "tag", "InterestAndDividendIncomeOperating"), GETPIVOTDATA("value", financials_wide!$A$3, "adsh", $E16, "tag", "InterestIncomeOperating")),"") -> 323770000 | I16: =IFERROR(GETPIVOTDATA("value", financials_wide!$A$3, "adsh", $E16, "tag", "Liabilities"),"") -> 5319838000 | J16: =IFERROR(F16-I16,"") -> 814058000 | K16: =IFERROR(GETPIVOTDATA("value", financials_wide!$A$3, "adsh", $E16, "tag", "NetIncomeLoss"),"") -> 56248000 | L16: =IFERROR(GETPIVOTDATA("value", financials_wide!$A$3, "adsh", $E16, "tag", "StockholdersEquity"),"") -> 814058000 | M16: =IFERROR(F16/L16,NA()) -> 7.5349619 | N16: =IFERROR(K16/F16,NA()) -> 0.0091700283 | O16: =IF(F16="","",IF(F16<=$P$2,"Small",IF(F16<=$Q$2,"Mid","Large"))) -> Mid | R16: =INDEX($C$2:$C$261,MATCH(S16,$K$2:$K$261,0)) -> KEYCORP /NEW/ | S16: =LARGE($K$2:$K$261,ROW()-1) -> 1829000000 | T16: 15
A17: 16 | B17: 6022 | C17: EAGLE FINANCIAL SERVICES INC | D17: 880641 | E17: 0000880641-26-000004 | F17: =IFERROR(GETPIVOTDATA("value", financials_wide!$A$3, "adsh", $E17, "tag", "Assets"),"") -> 1888626000 | G17: =IFERROR(GETPIVOTDATA("value", financials_wide!$A$3, "adsh", $E17, "tag", "EarningsPerShareBasic"),"") -> 1.59 | H17: =IFERROR(IFERROR(GETPIVOTDATA("value", financials_wide!$A$3, "adsh", $E17, "tag", "InterestAndDividendIncomeOperating"), GETPIVOTDATA("value", financials_wide!$A$3, "adsh", $E17, "tag", "InterestIncomeOperating")),"") -> 99005000 | I17: =IFERROR(GETPIVOTDATA("value", financials_wide!$A$3, "adsh", $E17, "tag", "Liabilities"),"") -> 1699787000 | J17: =IFERROR(F17-I17,"") -> 188839000 | K17: =IFERROR(GETPIVOTDATA("value", financials_wide!$A$3, "adsh", $E17, "tag", "NetIncomeLoss"),"") -> 8214000 | L17: =IFERROR(GETPIVOTDATA("value", financials_wide!$A$3, "adsh", $E17, "tag", "StockholdersEquity"),"") -> 188839000 | M17: =IFERROR(F17/L17,NA()) -> 10.00125 | N17: =IFERROR(K17/F17,NA()) -> 0.0043491935 | O17: =IF(F17="","",IF(F17<=$P$2,"Small",IF(F17<=$Q$2,"Mid","Large"))) -> Small
A18: 17 | B18: 6021 | C18: HAWTHORN BANCSHARES, INC. | D18: 893847 | E18: 0000893847-26-000037 | F18: =IFERROR(GETPIVOTDATA("value", financials_wide!$A$3, "adsh", $E18, "tag", "Assets"),"") -> 1894850000 | G18: =IFERROR(GETPIVOTDATA("value", financials_wide!$A$3, "adsh", $E18, "tag", "EarningsPerShareBasic"),"") -> 3.44 | H18: =IFERROR(IFERROR(GETPIVOTDATA("value", financials_wide!$A$3, "adsh", $E18, "tag", "InterestAndDividendIncomeOperating"), GETPIVOTDATA("value", financials_wide!$A$3, "adsh", $E18, "tag", "InterestIncomeOperating")),"") -> 97658000 | I18: =IFERROR(GETPIVOTDATA("value", financials_wide!$A$3, "adsh", $E18, "tag", "Liabilities"),"") -> 1720621000 | J18: =IFERROR(F18-I18,"") -> 174229000 | K18: =IFERROR(GETPIVOTDATA("value", financials_wide!$A$3, "adsh", $E18, "tag", "NetIncomeLoss"),"") -> 23801000 | L18: =IFERROR(GETPIVOTDATA("value", financials_wide!$A$3, "adsh", $E18, "tag", "StockholdersEquity"),"") -> 174229000 | M18: =IFERROR(F18/L18,NA()) -> 10.875629 | N18: =IFERROR(K18/F18,NA()) -> 0.012560889 | O18: =IF(F18="","",IF(F18<=$P$2,"Small",IF(F18<=$Q$2,"Mid","Large"))) -> Small
A19: 18 | B19: 6022 | C19: C & F FINANCIAL CORP | D19: 913341 | E19: 0000913341-26-000010 | F19: =IFERROR(GETPIVOTDATA("value", financials_wide!$A$3, "adsh", $E19, "tag", "Assets"),"") -> 2768494000 | G19: =IFERROR(GETPIVOTDATA("value", financials_wide!$A$3, "adsh", $E19, "tag", "EarningsPerShareBasic"),"") -> 8.29 | H19: =IFERROR(IFERROR(GETPIVOTDATA("value", financials_wide!$A$3, "adsh", $E19, "tag", "InterestAndDividendIncomeOperating"), GETPIVOTDATA("value", financials_wide!$A$3, "adsh", $E19, "tag", "InterestIncomeOperating")),"") -> 151499000 | I19: =IFERROR(GETPIVOTDATA("value", financials_wide!$A$3, "adsh", $E19, "tag", "Liabilities"),"") -> 2506146000 | J19: =IFERROR(F19-I19,"") -> 262348000 | K19: =IFERROR(GETPIVOTDATA("value", financials_wide!$A$3, "adsh", $E19, "tag", "NetIncomeLoss"),"") -> 26835000 | L19: =IFERROR(GETPIVOTDATA("value", financials_wide!$A$3, "adsh", $E19, "tag", "StockholdersEquity"),"") -> 261753000 | M19: =IFERROR(F19/L19,NA()) -> 10.576742 | N19: =IFERROR(K19/F19,NA()) -> 0.0096929955 | O19: =IF(F19="","",IF(F19<=$P$2,"Small",IF(F19<=$Q$2,"Mid","Large"))) -> Mid
A20: 19 | B20: 6022 | C20: UNITY BANCORP INC /NJ/ | D20: 920427 | E20: 0000920427-26-000012 | F20: =IFERROR(GETPIVOTDATA("value", financials_wide!$A$3, "adsh", $E20, "tag", "Assets"),"") -> 2966652000 | G20: =IFERROR(GETPIVOTDATA("value", financials_wide!$A$3, "adsh", $E20, "tag", "EarningsPerShareBasic"),"") -> 5.78 | H20: =IFERROR(IFERROR(GETPIVOTDATA("value", financials_wide!$A$3, "adsh", $E20, "tag", "InterestAndDividendIncomeOperating"), GETPIVOTDATA("value", financials_wide!$A$3, "adsh", $E20, "tag", "InterestIncomeOperating")),"") -> 173628000 | I20: =IFERROR(GETPIVOTDATA("value", financials_wide!$A$3, "adsh", $E20, "tag", "Liabilities"),"") -> 2621021000 | J20: =IFERROR(F20-I20,"") -> 345631000 | K20: =IFERROR(GETPIVOTDATA("value", financials_wide!$A$3, "adsh", $E20, "tag", "NetIncomeLoss"),"") -> 57951000 | L20: =IFERROR(GETPIVOTDATA("value", financials_wide!$A$3, "adsh", $E20, "tag", "StockholdersEquity"),"") -> 345631000 | M20: =IFERROR(F20/L20,NA()) -> 8.5832926 | N20: =IFERROR(K20/F20,NA()) -> 0.019534142 | O20: =IF(F20="","",IF(F20<=$P$2,"Small",IF(F20<=$Q$2,"Mid","Large"))) -> Mid
A21: 20 | B21: 6022 | C21: NORWOOD FINANCIAL CORP | D21: 1013272 | E21: 0001013272-26-000003 | F21: =IFERROR(GETPIVOTDATA("value", financials_wide!$A$3, "adsh", $E21, "tag", "Assets"),"") -> 2424842000 | G21: =IFERROR(GETPIVOTDATA("value", financials_wide!$A$3, "adsh", $E21, "tag", "EarningsPerShareBasic"),"") -> 3.01 | H21: =IFERROR(IFERROR(GETPIVOTDATA("value", financials_wide!$A$3, "adsh", $E21, "tag", "InterestAndDividendIncomeOperating"), GETPIVOTDATA("value", financials_wide!$A$3, "adsh", $E21, "tag", "InterestIncomeOperating")),"") -> 126528000 | I21: =IFERROR(GETPIVOTDATA("value", financials_wide!$A$3, "adsh", $E21, "tag", "Liabilities"),"") -> 2182685000 | J21: =IFERROR(F21-I21,"") -> 242157000 | K21: =IFERROR(GETPIVOTDATA("value", financials_wide!$A$3, "adsh", $E21, "tag", "NetIncomeLoss"),"") -> 27755000 | L21: =IFERROR(GETPIVOTDATA("value", financials_wide!$A$3, "adsh", $E21, "tag", "StockholdersEquity"),"") -> 242157000 | M21: =IFERROR(F21/L21,NA()) -> 10.013512 | N21: =IFERROR(K21/F21,NA()) -> 0.011446107 | O21: =IF(F21="","",IF(F21<=$P$2,"Small",IF(F21<=$Q$2,"Mid","Large"))) -> Small
A22: 21 | B22: 6022 | C22: EAGLE BANCORP INC | D22: 1050441 | E22: 0001050441-26-000021 | F22: =IFERROR(GETPIVOTDATA("value", financials_wide!$A$3, "adsh", $E22, "tag", "Assets"),"") -> 10497203000 | G22: =IFERROR(GETPIVOTDATA("value", financials_wide!$A$3, "adsh", $E22, "tag", "EarningsPerShareBasic"),"") -> -4.55 | H22: =IFERROR(IFERROR(GETPIVOTDATA("value", financials_wide!$A$3, "adsh", $E22, "tag", "InterestAndDividendIncomeOperating"), GETPIVOTDATA("value", financials_wide!$A$3, "adsh", $E22, "tag", "InterestIncomeOperating")),"") -> 604482000 | I22: =IFERROR(GETPIVOTDATA("value", financials_wide!$A$3, "adsh", $E22, "tag", "Liabilities"),"") -> 9365920000 | J22: =IFERROR(F22-I22,"") -> 1131283000 | K22: =IFERROR(GETPIVOTDATA("value", financials_wide!$A$3, "adsh", $E22, "tag", "NetIncomeLoss"),"") -> -138052000 | L22: =IFERROR(GETPIVOTDATA("value", financials_wide!$A$3, "adsh", $E22, "tag", "StockholdersEquity"),"") -> 1131283000 | M22: =IFERROR(F22/L22,NA()) -> 9.2790248 | N22: =IFERROR(K22/F22,NA()) -> -0.013151313 | O22: =IF(F22="","",IF(F22<=$P$2,"Small",IF(F22<=$Q$2,"Mid","Large"))) -> Mid
A23: 22 | B23: 6022 | C23: RED RIVER BANCSHARES INC | D23: 1071236 | E23: 0001071236-26-000027 | F23: =IFERROR(GETPIVOTDATA("value", financials_wide!$A$3, "adsh", $E23, "tag", "Assets"),"") -> 3350910000 | G23: =IFERROR(GETPIVOTDATA("value", financials_wide!$A$3, "adsh", $E23, "tag", "EarningsPerShareBasic"),"") -> 6.4 | H23: =IFERROR(IFERROR(GETPIVOTDATA("value", financials_wide!$A$3, "adsh", $E23, "tag", "InterestAndDividendIncomeOperating"), GETPIVOTDATA("value", financials_wide!$A$3, "adsh", $E23, "tag", "InterestIncomeOperating")),"") -> 149886000 | I23: =IFERROR(GETPIVOTDATA("value", financials_wide!$A$3, "adsh", $E23, "tag", "Liabilities"),"") -> 2985760000 | J23: =IFERROR(F23-I23,"") -> 365150000 | K23: =IFERROR(GETPIVOTDATA("value", financials_wide!$A$3, "adsh", $E23, "tag", "NetIncomeLoss"),"") -> 42764000 | L23: =IFERROR(GETPIVOTDATA("value", financials_wide!$A$3, "adsh", $E23, "tag", "StockholdersEquity"),"") -> 365150000 | M23: =IFERROR(F23/L23,NA()) -> 9.1768041 | N23: =IFERROR(K23/F23,NA()) -> 0.012761906 | O23: =IF(F23="","",IF(F23<=$P$2,"Small",IF(F23<=$Q$2,"Mid","Large"))) -> Mid
A24: 23 | B24: 6022 | C24: REPUBLIC BANCORP INC /KY/ | D24: 921557 | E24: 0001104659-26-024523 | F24: =IFERROR(GETPIVOTDATA("value", financials_wide!$A$3, "adsh", $E24, "tag", "Assets"),"") -> 7042061000 | G24: =IFERROR(GETPIVOTDATA("value", financials_wide!$A$3, "adsh", $E24, "tag", "EarningsPerShareBasic"),"") -> 0 | H24: =IFERROR(IFERROR(GETPIVOTDATA("value", financials_wide!$A$3, "adsh", $E24, "tag", "InterestAndDividendIncomeOperating"), GETPIVOTDATA("value", financials_wide!$A$3, "adsh", $E24, "tag", "InterestIncomeOperating")),"") -> 438513000 | I24: =IFERROR(GETPIVOTDATA("value", financials_wide!$A$3, "adsh", $E24, "tag", "Liabilities"),"") -> 5939768000 | J24: =IFERROR(F24-I24,"") -> 1102293000 | K24: =IFERROR(GETPIVOTDATA("value", financials_wide!$A$3, "adsh", $E24, "tag", "NetIncomeLoss"),"") -> 131317000 | L24: =IFERROR(GETPIVOTDATA("value", financials_wide!$A$3, "adsh", $E24, "tag", "StockholdersEquity"),"") -> 1102293000 | M24: =IFERROR(F24/L24,NA()) -> 6.3885564 | N24: =IFERROR(K24/F24,NA()) -> 0.018647524 | O24: =IF(F24="","",IF(F24<=$P$2,"Small",IF(F24<=$Q$2,"Mid","Large"))) -> Mid
A25: 24 | B25: 6022 | C25: CITIZENS & NORTHERN CORP | D25: 810958 | E25: 0001104659-26-024613 | F25: =IFERROR(GETPIVOTDATA("value", financials_wide!$A$3, "adsh", $E25, "tag", "Assets"),"") -> 3132469000 | G25: =IFERROR(GETPIVOTDATA("value", financials_wide!$A$3, "adsh", $E25, "tag", "EarningsPerShareBasic"),"") -> 1.46 | H25: =IFERROR(IFERROR(GETPIVOTDATA("value", financials_wide!$A$3, "adsh", $E25, "tag", "InterestAndDividendIncomeOperating"), GETPIVOTDATA("value", financials_wide!$A$3, "adsh", $E25, "tag", "InterestIncomeOperating")),"") -> 139217000 | I25: =IFERROR(GETPIVOTDATA("value", financials_wide!$A$3, "adsh", $E25, "tag", "Liabilities"),"") -> 2790755000 | J25: =IFERROR(F25-I25,"") -> 341714000 | K25: =IFERROR(GETPIVOTDATA("value", financials_wide!$A$3, "adsh", $E25, "tag", "NetIncomeLoss"),"") -> 23427000 | L25: =IFERROR(GETPIVOTDATA("value", financials_wide!$A$3, "adsh", $E25, "tag", "StockholdersEquity"),"") -> 341714000 | M25: =IFERROR(F25/L25,NA()) -> 9.166932 | N25: =IFERROR(K25/F25,NA()) -> 0.0074787652 | O25: =IF(F25="","",IF(F25<=$P$2,"Small",IF(F25<=$Q$2,"Mid","Large"))) -> Mid
A26: 25 | B26: 6022 | C26: FLUSHING FINANCIAL CORP | D26: 923139 | E26: 0001104659-26-024646 | F26: =IFERROR(GETPIVOTDATA("value", financials_wide!$A$3, "adsh", $E26, "tag", "Assets"),"") -> 8693302000 | G26: =IFERROR(GETPIVOTDATA("value", financials_wide!$A$3, "adsh", $E26, "tag", "EarningsPerShareBasic"),"") -> 0.54 | H26: =IFERROR(IFERROR(GETPIVOTDATA("value", financials_wide!$A$3, "adsh", $E26, "tag", "InterestAndDividendIncomeOperating"), GETPIVOTDATA("value", financials_wide!$A$3, "adsh", $E26, "tag", "InterestIncomeOperating")),"") -> 466229000 | I26: =IFERROR(GETPIVOTDATA("value", financials_wide!$A$3, "adsh", $E26, "tag", "Liabilities"),"") -> 7985327000 | J26: =IFERROR(F26-I26,"") -> 707975000 | K26: =IFERROR(GETPIVOTDATA("value", financials_wide!$A$3, "adsh", $E26, "tag", "NetIncomeLoss"),"") -> 18880000 | L26: =IFERROR(GETPIVOTDATA("value", financials_wide!$A$3, "adsh", $E26, "tag", "StockholdersEquity"),"") -> 707975000 | M26: =IFERROR(F26/L26,NA()) -> 12.279109 | N26: =IFERROR(K26/F26,NA()) -> 0.002171787 | O26: =IF(F26="","",IF(F26<=$P$2,"Small",IF(F26<=$Q$2,"Mid","Large"))) -> Mid
A27: 26 | B27: 6022 | C27: GREAT SOUTHERN BANCORP, INC. | D27: 854560 | E27: 0001104659-26-024659 | F27: =IFERROR(GETPIVOTDATA("value", financials_wide!$A$3, "adsh", $E27, "tag", "Assets"),"") -> 5598606000 | G27: =IFERROR(GETPIVOTDATA("value", financials_wide!$A$3, "adsh", $E27, "tag", "EarningsPerShareBasic"),"") -> 6.23 | H27: =IFERROR(IFERROR(GETPIVOTDATA("value", financials_wide!$A$3, "adsh", $E27, "tag", "InterestAndDividendIncomeOperating"), GETPIVOTDATA("value", financials_wide!$A$3, "adsh", $E27, "tag", "InterestIncomeOperating")),"") -> 313732000 | I27: =IFERROR(GETPIVOTDATA("value", financials_wide!$A$3, "adsh", $E27, "tag", "Liabilities"),"") -> 4962480000 | J27: =IFERROR(F27-I27,"") -> 636126000 | K27: =IFERROR(GETPIVOTDATA("value", financials_wide!$A$3, "adsh", $E27, "tag", "NetIncomeLoss"),"") -> 70973000 | L27: =IFERROR(GETPIVOTDATA("value", financials_wide!$A$3, "adsh", $E27, "tag", "StockholdersEquity"),"") -> 636126000 | M27: =IFERROR(F27/L27,NA()) -> 8.801096 | N27: =IFERROR(K27/F27,NA()) -> 0.012676906 | O27: =IF(F27="","",IF(F27<=$P$2,"Small",IF(F27<=$Q$2,"Mid","Large"))) -> Mid
A28: 27 | B28: 6021 | C28: FIRST UNITED CORP/MD/ | D28: 763907 | E28: 0001104659-26-025836 | F28: =IFERROR(GETPIVOTDATA("value", financials_wide!$A$3, "adsh", $E28, "tag", "Assets"),"") | G28: =IFERROR(GETPIVOTDATA("value", financials_wide!$A$3, "adsh", $E28, "tag", "EarningsPerShareBasic"),"") | H28: =IFERROR(IFERROR(GETPIVOTDATA("value", financials_wide!$A$3, "adsh", $E28, "tag", "InterestAndDividendIncomeOperating"), GETPIVOTDATA("value", financials_wide!$A$3, "adsh", $E28, "tag", "InterestIncomeOperating")),"") | I28: =IFERROR(GETPIVOTDATA("value", financials_wide!$A$3, "adsh", $E28, "tag", "Liabilities"),"") | J28: =IFERROR(F28-I28,"") | K28: =IFERROR(GETPIVOTDATA("value", financials_wide!$A$3, "adsh", $E28, "tag", "NetIncomeLoss"),"") | L28: =IFERROR(GETPIVOTDATA("value", financials_wide!$A$3, "adsh", $E28, "tag", "StockholdersEquity"),"") | M28: =IFERROR(F28/L28,NA()) -> #N/A | N28: =IFERROR(K28/F28,NA()) -> #N/A | O28: =IF(F28="","",IF(F28<=$P$2,"Small",IF(F28<=$Q$2,"Mid","Large")))
... A261: 260 | B261: 6021 | C261: BURKE & HERBERT FINANCIAL SERVICES CORP. | D261: 1964333 | E261: 0001964333-26-000016 | F261: =IFERROR(GETPIVOTDATA("value", financials_wide!$A$3, "adsh", $E261, "tag", "Assets"),"") -> 7920626000 | G261: =IFERROR(GETPIVOTDATA("value", financials_wide!$A$3, "adsh", $E261, "tag", "EarningsPerShareBasic"),"") -> 7.76 | H261: =IFERROR(IFERROR(GETPIVOTDATA("value", financials_wide!$A$3, "adsh", $E261, "tag", "InterestAndDividendIncomeOperating"), GETPIVOTDATA("value", financials_wide!$A$3, "adsh", $E261, "tag", "InterestIncomeOperating")),"") -> 0 | I261: =IFERROR(GETPIVOTDATA("value", financials_wide!$A$3, "adsh", $E261, "tag", "Liabilities"),"") -> 7065977000 | J261: =IFERROR(F261-I261,"") -> 854649000 | K261: =IFERROR(GETPIVOTDATA("value", financials_wide!$A$3, "adsh", $E261, "tag", "NetIncomeLoss"),"") -> 117306000 | L261: =IFERROR(GETPIVOTDATA("value", financials_wide!$A$3, "adsh", $E261, "tag", "StockholdersEquity"),"") -> 854649000 | M261: =IFERROR(F261/L261,NA()) -> 9.2676947 | N261: =IFERROR(K261/F261,NA()) -> 0.014810193 | O261: =IF(F261="","",IF(F261<=$P$2,"Small",IF(F261<=$Q$2,"Mid","Large"))) -> Mid

Sheet companies
A1: adsh | B1: cik | C1: name | D1: sic | E1: fye | F1: form | G1: period
A2: 0000039311-26-000009 | B2: 39311 | C2: INDEPENDENT BANK CORP /MI/ | D2: 6022 | E2: 1231 | F2: 10-K | G2: 20251231
A3: 0000706129-26-000024 | B3: 706129 | C3: HORIZON BANCORP INC /IN/ | D3: 6022 | E3: 1231 | F3: 10-K | G3: 20251231
A4: 0000706863-26-000029 | B4: 706863 | C4: UNION BANKSHARES INC | D4: 6022 | E4: 1231 | F4: 10-K | G4: 20251231
A5: 0000711669-26-000007 | B5: 711669 | C5: COLONY BANKCORP INC | D5: 6022 | E5: 1231 | F5: 10-K | G5: 20251231
A6: 0000714562-26-000014 | B6: 714562 | C6: FIRST FINANCIAL CORP /IN/ | D6: 6022 | E6: 1231 | F6: 10-K | G6: 20251231
A7: 0000717538-26-000037 | B7: 717538 | C7: ARROW FINANCIAL CORP | D7: 6021 | E7: 1231 | F7: 10-K | G7: 20251231
A8: 0000723646-26-000016 | B8: 723646 | C8: FRANKLIN FINANCIAL SERVICES CORP /PA/ | D8: 6022 | E8: 1231 | F8: 10-K | G8: 20251231
A9: 0000732417-26-000022 | B9: 732417 | C9: HILLS BANCORPORATION | D9: 6022 | E9: 1231 | F9: 10-K | G9: 20251231
A10: 0000736772-26-000031 | B10: 736772 | C10: CNB FINANCIAL CORP/PA | D10: 6022 | E10: 1231 | F10: 10-K | G10: 20251231
A11: 0000737875-26-000009 | B11: 737875 | C11: FIRST KEYSTONE CORP | D11: 6022 | E11: 1231 | F11: 10-K | G11: 20251231
A12: 0000750686-26-000010 | B12: 750686 | C12: CAMDEN NATIONAL CORP | D12: 6021 | E12: 1231 | F12: 10-K | G12: 20251231
A13: 0000765207-26-000067 | B13: 765207 | C13: FIRST BANCORP, INC /ME/ | D13: 6021 | E13: 1231 | F13: 10-K | G13: 20251231
... A261: 0001964333-26-000016 | B261: 1964333 | C261: BURKE & HERBERT FINANCIAL SERVICES CORP. | D261: 6021 | E261: 1231 | F261: 10-K | G261: 20251231

Sheet financials_wide
A3: Sum of value | B3: Column Labels
A4: Row Labels | B4: Assets | C4: EarningsPerShareBasic | D4: InterestAndDividendIncomeOperating | E4: InterestIncomeOperating | F4: Liabilities | G4: NetIncomeLoss | H4: StockholdersEquity | I4: Grand Total
A5: 0000007789-26-000071 | B5: 45202596000 | C5: 2.79 | D5: 2172756000 | F5: 40227249000 | G5: 474777000 | H5: 4975347000 | I5: 9.3052725e+10
A6: 0000022356-26-000069 | B6: 32915089000 | C6: 4.04 | D6: 1483723000 | F6: 29100317000 | G6: 566251000 | H6: 3791371000 | I6: 6.7856751e+10
A7: 0000034782-26-000011 | B7: 9055270000 | C7: 6.41 | D7: 514394000 | F7: 7737180000 | H7: 1274971000 | I7: 1.8581815e+10
A8: 0000035527-26-000124 | B8: 214376000000 | C8: 3.56 | D8: 9903000000 | F8: 192652000000 | G8: 2522000000 | H8: 21724000000 | I8: 4.41177e+11
A9: 0000036104-26-000011 | B9: 692345000000 | C9: 4.62 | D9: 30970000000 | F9: 626694000000 | G9: 7570000000 | H9: 65193000000 | I9: 1.422772e+12
A10: 0000036270-26-000010 | B10: 213510000000 | C10: 17.1 | D10: 10486000000 | F10: 184333000000 | G10: 2851000000 | H10: 29177000000 | I10: 4.40357e+11
A11: 0000036966-26-000051 | B11: 83876000000 | C11: 1.89 | E11: 4186000000 | F11: 74734000000 | G11: 982000000 | H11: 8847000000 | I11: 1.72625e+11
A12: 0000037808-26-000007 | B12: 50229000000 | C12: 1.57 | D12: 2326000000 | F12: 43470000000 | G12: 565000000 | H12: 6759000000 | I12: 1.03349e+11
A13: 0000039263-26-000011 | B13: 53041424000 | C13: 9.92 | D13: 2420747000 | F13: 48468388000 | G13: 648557000 | H13: 4573036000 | I13: 1.0915215e+11
A14: 0000039311-26-000009 | B14: 5505720000 | C14: 3.3 | D14: 269737000 | F14: 5002769000 | G14: 68541000 | H14: 502951000 | I14: 1.1349718e+10
A15: 0000040729-26-000005 | B15: 196002000000 | C15: 2.39 | F15: 180504000000 | G15: 852000000 | H15: 15498000000 | I15: 3.92856e+11
A16: 0000046195-26-000015 | B16: 24176364000 | C16: 4.67 | D16: 887823000 | F16: 22325152000 | G16: 205902000 | H16: 1851212000 | I16: 4.9446453e+10
A17: 0000049196-26-000015 | B17: 225106000000 | C17: 1.41 | D17: 10310000000 | F17: 200727000000 | G17: 2211000000 | H17: 24342000000 | I17: 4.62696e+11
A18: 0000070858-26-000157 | B18: 3411738000000 | C18: 3.86 | D18: 138566000000 | F18: 3108495000000 | G18: 30509000000 | H18: 303243000000 | I18: 6.992551e+12
A19: 0000072971-26-000133 | B19: 2148631000000 | C19: 6.34 | D19: 87314000000 | F19: 1965593000000 | G19: 21338000000 | H19: 181117000000 | I19: 4.403993e+12
A20: 0000073124-26-000016 | B20: 177132700000 | C20: 8.78 | D20: 8624600000 | F20: 164174800000 | G20: 1736900000 | H20: 12957900000 | I20: 3.646269e+11
A21: 0000083246-26-000005 | B21: 172410000000 | D21: 7502000000 | F21: 159971000000 | G21: 1101000000 | H21: 12439000000 | I21: 353423000000
A22: 0000092230-26-000030 | B22: 547538000000 | C22: 3.87 | D22: 24542000000 | F22: 482349000000 | H22: 65189000000 | I22: 1.119618e+12
A23: 0000093751-26-000124 | B23: 366047000000 | C23: 9.55 | D23: 11644000000 | F23: 338206000000 | G23: 2945000000 | H23: 27841000000 | I23: 7.46683e+11
A24: 0000102212-26-000012 | B24: 8436897000 | C24: 3.16 | D24: 430486000 | F24: 7493579000 | G24: 90757000 | H24: 943318000 | I24: 1.7395037e+10
A25: 0000109380-26-000046 | B25: 88990000000 | C25: 6.01 | D25: 4184000000 | F25: 81810000000 | G25: 899000000 | H25: 7180000000 | I25: 1.83063e+11
A26: 0000314489-26-000013 | B26: 18104736000 | C26: 1.49 | D26: 893860000 | F26: 15635754000 | G26: 135262000 | H26: 2468982000 | I26: 3.7238594e+10
A27: 0000318300-26-000099 | B27: 9649630000 | C27: 3.03 | D27: 514306000 | F27: 8443028000 | G27: 106778000 | H27: 1206602000 | I27: 1.9920344e+10
A28: 0000351569-26-000050 | B28: 27515879000 | C28: 6.02 | D28: 1394525000 | F28: 23439851000 | G28: 412154000 | H28: 4076028000 | I28: 5.6838437e+10
A29: 0000356171-26-000010 | B29: 9822063000 | C29: 3.72 | D29: 470572000 | F29: 8494062000 | G29: 121558000 | H29: 1328001000 | I29: 2.0236256e+10
A30: 0000700564-26-000006 | B30: 32118400000 | C30: 2.1 | D30: 1616874000 | F30: 28627953000 | G30: 391609000 | H30: 3490447000 | I30: 6.6245283e+10
A31: 0000701347-26-000021 | B31: 7409241000 | C31: 2.88 | D31: 314162000 | F31: 6816660000 | G31: 77480000 | H31: 592581000 | I31: 1.5210124e+10
A32: 0000705432-26-000034 | B32: 8514590000 | C32: 2.3 | D32: 403074000 | F32: 7666975000 | G32: 69220000 | H32: 847615000 | I32: 1.7501474e+10
A33: 0000706129-26-000024 | B33: 6436611000 | C33: -3.24 | D33: 362777000 | F33: 5748360000 | G33: -150482000 | H33: 688251000 | I33: 1.3085517e+10
A34: 0000706863-26-000029 | B34: 1617191000 | C34: 2.43 | D34: 75788000 | F34: 1536327000 | G34: 11080000 | H34: 80864000 | I34: 3.32125e+09
... A36: 0000708955-26-000028 | B36: 21129379000 | C36: 2.68 | D36: 1001904000 | F36: 18360163000 | G36: 255605000 | H36: 2769216000 | I36: 4.3516267e+10
A37: 0000711669-26-000007 | B37: 3735401000 | C37: 1.59 | D37: 149952000 | E37: 19436000 | F37: 3359481000 | G37: 28253000 | H37: 375920000 | I37: 7.668443e+09
A38: 0000712534-26-000022 | B38: 19025101000 | C38: 3.9 | D38: 924792000 | F38: 16558434000 | G38: 226001000 | H38: 2466667000 | I38: 3.9200995e+10
A39: 0000712537-26-000013 | B39: 12343036000 | C39: 1.48 | D39: 632688000 | F39: 10788660000 | G39: 152302000 | H39: 1554376000 | I39: 2.5471062e+10
A40: 0000713676-26-000020 | B40: 573572000000 | C40: 16.6 | D40: 25307000000 | F40: 512936000000 | H40: 60585000000 | I40: 1.1724e+12
A41: 0000714310-26-000017 | B41: 64132725000 | C41: 1.02 | D41: 3232484000 | F41: 56325027000 | G41: 597983000 | H41: 7807698000 | I41: 1.3209592e+11
A42: 0000714395-26-000011 | B42: 8388780000 | C42: 3.06 | D42: 420089000 | F42: 7226455000 | G42: 112635000 | H42: 1162325000 | I42: 1.7310284e+10
A43: 0000714562-26-000014 | B43: 5756126000 | C43: 6.68 | D43: 305588000 | F43: 5105257000 | G43: 79208000 | H43: 650869000 | I43: 1.1897048e+10
A44: 0000715072-26-000017 | B44: 26751426000 | C44: 2.09 | D44: 1262259000 | F44: 22866521000 | G44: 181272000 | H44: 3884905000 | I44: 5.4946383e+10
A45: 0000717538-26-000037 | B45: 4445862000 | C45: 2.65 | F45: 4014010000 | G45: 43953000 | H45: 431852000 | I45: 8.935677e+09
A46: 0000719220-26-000030 | B46: 9870980000 | C46: 3.51 | D46: 516490000 | F46: 8407103000 | G46: 134230000 | H46: 1463877000 | I46: 2.039268e+10
A47: 0000721994-26-000018 | B47: 6990022000 | C47: 4.02 | D47: 373735000 | F47: 6227530000 | G47: 103361000 | H47: 762403000 | I47: 1.4457051e+10
A48: 0000723646-26-000016 | B48: 2239018000 | C48: 4.76 | D48: 114371000 | F48: 2063776000 | G48: 21226000 | H48: 175242000 | I48: 4.613633e+09
A49: 0000726601-26-000007 | B49: 4385765000 | C49: 3.61 | D49: 204387000 | F49: 3832914000 | G49: 61557000 | H49: 552851000 | I49: 9.037474e+09
A50: 0000726854-26-000062 | B50: 6722018000 | C50: 8.94 | D50: 321216000 | F50: 5912338000 | G50: 130485000 | H50: 809680000 | I50: 1.3895737e+10
A51: 0000732417-26-000022 | B51: 4647870000 | C51: 6.82 | E51: 233774000 | F51: 4045161000 | G51: 60502000 | H51: 548234000 | I51: 9.535541e+09
A52: 0000736772-26-000031 | B52: 8396435000 | C52: 2.5 | D52: 392345000 | F52: 7524308000 | G52: 66131000 | H52: 872127000 | I52: 1.7251346e+10
A53: 0000737468-26-000034 | B53: 6621694000 | C53: 2.72 | D53: 318091000 | F53: 6078110000 | G53: 52244000 | H53: 543584000 | I53: 1.3613723e+10
A54: 0000737875-26-000009 | B54: 1530977000 | C54: 0.99 | D54: 77199000 | F54: 1417917000 | G54: 6152000 | H54: 113060000 | I54: 3.145305e+09
A55: 0000750686-26-000010 | B55: 6974584000 | C55: 3.86 | D55: 320655000 | F55: 6278026000 | G55: 65160000 | H55: 696558000 | I55: 1.4334983e+10
A56: 0000759944-26-000028 | B56: 226351000000 | C56: 3.9 | D56: 9663000000 | F56: 200034000000 | G56: 1831000000 | H56: 26317000000 | I56: 4.64196e+11
A57: 0000765207-26-000067 | B57: 3166303000 | C57: 3.1 | D57: 160271000 | F57: 2883160000 | G57: 34394000 | H57: 283143000 | I57: 6.527271e+09
A58: 0000775215-26-000025 | B58: 5071390000 | C58: 2.44 | D58: 255784000 | F58: 4455892000 | G58: 77008000 | H58: 615498000 | I58: 1.0475572e+10
A59: 0000776901-26-000058 | B59: 24912896000 | C59: 4.44 | D59: 1022400000 | F59: 21347168000 | G59: 205122000 | H59: 3565728000 | I59: 5.1053314e+10
A60: 0000798941-26-000015 | B60: 229698000000 | C60: 165.24 | D60: 11778000000 | F60: 207460000000 | G60: 2206000000 | H60: 22238000000 | I60: 4.7338e+11
A61: 0000801337-26-000008 | B61: 84073663000 | C61: 5.91 | D61: 4021508000 | F61: 74581427000 | G61: 1002802000 | H61: 9492236000 | I61: 1.7317164e+11
A62: 0000805676-26-000017 | B62: 9805013000 | C62: 11.18 | D62: 544540000 | F62: 8452220000 | G62: 180073000 | I62: 1.8981846e+10
A63: 0000811589-26-000051 | B63: 12668339000 | C63: 2.68 | D63: 557235000 | F63: 11014171000 | G63: 111048000 | H63: 1654168000 | I63: 2.6004961e+10
A64: 0000811830-26-000005 | B64: 164572121000 | D64: 12436658000 | F64: 146627414000 | G64: 1645158000 | H64: 15944707000 | I64: 341226058000
A65: 0000828944-26-000006 | B65: 21314076000 | C65: 5.11 | D65: 1019688000 | F65: 18586001000 | G65: 287349000 | H65: 2738545000 | I65: 4.3945659e+10
A66: 0000831001-26-000011 | B66: 2657202000000 | C66: 7.11 | D66: 142864000000 | F66: 2443380000000 | G66: 14306000000 | H66: 212291000000 | I66: 5.470043e+12
A67: 0000842517-26-000069 | B67: 2209448000 | C67: 2.56 | D67: 96035000 | F67: 1978052000 | G67: 18910000 | H67: 231396000 | I67: 4.533841e+09
A68: 0000846617-26-000013 | B68: 15341631000 | C68: 2.36 | D68: 685442000 | F68: 13865862000 | G68: 110682000 | H68: 1475769000 | I68: 3.1479386e+10
A69: 0000857855-26-000008 | B69: 28002554000 | C69: 2.62 | D69: 1382939000 | F69: 24363868000 | G69: 328095000 | H69: 3638686000 | I69: 5.7716142e+10
A70: 0000860413-26-000011 | B70: 26640600000 | C70: 2.95 | D70: 1178000000 | F70: 23193600000 | G70: 302100000 | H70: 3447000000 | I70: 5.47613e+10
A71: 0000868671-26-000023 | B71: 31978063000 | C71: 2 | D71: 1295797000 | F71: 27764242000 | G71: 239028000 | H71: 4213821000 | I71: 65490951002
A72: 0000875357-26-000013 | B72: 52237501000 | C72: 9.17 | D72: 2531268000 | F72: 46316821000 | G72: 577990000 | H72: 5918646000 | I72: 1.0758223e+11
A73: 0000879635-26-000026 | B73: 6133896000 | C73: 2.59 | D73: 323770000 | F73: 5319838000 | G73: 56248000 | H73: 814058000 | I73: 1.264781e+10
A74: 0000880641-26-000004 | B74: 1888626000 | C74: 1.59 | D74: 99005000 | F74: 1699787000 | G74: 8214000 | H74: 188839000 | I74: 3.884471e+09
A75: 0000883948-26-000021 | B75: 37585754000 | C75: 2.03 | D75: 1821487000 | F75: 32579356000 | G75: 273715000 | H75: 5006398000 | I75: 7.726671e+10
A76: 0000887343-26-000088 | B76: 66832000000 | C76: 2.31 | D76: 2916000000 | F76: 58992000000 | G76: 550000000 | H76: 7840000000 | I76: 1.3713e+11
... A80: 0000927628-26-000024 | B80: 669009000000 | C80: 4.03 | D80: 58696000000 | F80: 555393000000 | G80: 2453000000 | H80: 113616000000 | I80: 1.399167e+12
A81: 0000946673-26-000009 | B81: 16354488000 | C81: 5.67 | E81: 804955000 | F81: 14408191000 | G81: 195382000 | H81: 1946297000 | I81: 3.3709313e+10
A82: 0001004702-26-000015 | B82: 14564317000 | C82: 1.17 | D82: 642454000 | F82: 12901767000 | G82: 70978000 | H82: 1662550000 | I82: 2.9842066e+10
A83: 0001005817-26-000027 | B83: 8668268000 | C83: 11.3 | D83: 382074000 | F83: 7729891000 | G83: 161071000 | I83: 1.6941304e+10
A84: 0001013272-26-000003 | B84: 2424842000 | C84: 3.01 | D84: 126528000 | F84: 2182685000 | G84: 27755000 | H84: 242157000 | I84: 5.003967e+09
A85: 0001015328-26-000007 | B85: 71142046000 | C85: 11.57 | D85: 3728033000 | F85: 63883331000 | G85: 823844000 | H85: 7258715000 | I85: 1.4683597e+11
A86: 0001025835-26-000058 | B86: 17300884000 | C86: 5.34 | D86: 888410000 | F86: 15261498000 | G86: 201374000 | H86: 2039386000 | I86: 3.5691552e+10
A87: 0001030469-26-000008 | B87: 12465657000 | C87: 4.6 | D87: 780936000 | F87: 11075652000 | G87: 205103000 | H87: 1390005000 | I87: 2.5917353e+10
A88: 0001035092-26-000014 | B88: 6258818000 | C88: 1.78 | D88: 310028000 | F88: 5668945000 | G88: 59506000 | H88: 589873000 | I88: 1.288717e+10
A89: 0001050441-26-000021 | B89: 10497203000 | C89: -4.55 | D89: 604482000 | F89: 9365920000 | G89: -138052000 | H89: 1131283000 | I89: 2.1460836e+10
A90: 0001057706-26-000007 | B90: 19132892000 | C90: 2.16 | D90: 1123156000 | F90: 17166027000 | G90: 344866000 | H90: 1966865000 | I90: 3.9733806e+10
A91: 0001069157-26-000009 | B91: 80434997000 | C91: 9.58 | D91: 4293396000 | F91: 71535795000 | G91: 1325188000 | H91: 8899202000 | I91: 1.6648858e+11
A92: 0001071236-26-000027 | B92: 3350910000 | C92: 6.4 | D92: 149886000 | F92: 2985760000 | G92: 42764000 | H92: 365150000 | I92: 6.89447e+09
A93: 0001077428-26-000010 | B93: 31540274000 | C93: 6.86 | D93: 1771785000 | F93: 27908892000 | G93: 330244000 | H93: 3631382000 | I93: 6.5182577e+10
A94: 0001104659-26-015264 | B94: 15844994000 | C94: 2.64 | D94: 784050000 | F94: 13647388000 | G94: 165591000 | H94: 2168401000 | I94: 3.2610424e+10
A95: 0001104659-26-017884 | B95: 67197412000 | C95: 7.9 | D95: 3379498000 | F95: 58138304000 | G95: 798667000 | H95: 9059108000 | I95: 1.3857299e+11
... A106: 0001104659-26-021651 | B106: 17303296000 | C106: 3.98 | D106: 699275000 | F106: 15297262000 | G106: 210455000 | H106: 2006034000 | I106: 3.5516322e+10
A107: 0001104659-26-024523 | B107: 7042061000 | D107: 438513000 | F107: 5939768000 | G107: 131317000 | H107: 1102293000 | I107: 14653952000
A108: 0001104659-26-024613 | B108: 3132469000 | C108: 1.46 | D108: 139217000 | F108: 2790755000 | G108: 23427000 | H108: 341714000 | I108: 6.427582e+09
A109: 0001104659-26-024646 | B109: 8693302000 | C109: 0.54 | D109: 466229000 | F109: 7985327000 | G109: 18880000 | H109: 707975000 | I109: 1.7871713e+10
A110: 0001104659-26-024659 | B110: 5598606000 | C110: 6.23 | D110: 313732000 | F110: 4962480000 | G110: 70973000 | H110: 636126000 | I110: 1.1581917e+10
A111: 0001104659-26-027217 | B111: 4683891000 | C111: 2.32 | D111: 209519000 | F111: 4151350000 | G111: 36919000 | H111: 532541000 | I111: 9.61422e+09
A112: 0001104659-26-027378 | B112: 2332550000 | C112: 1.49 | D112: 113257000 | F112: 2066912000 | G112: 21233000 | H112: 265638000 | I112: 4.79959e+09
A113: 0001104659-26-027651 | B113: 2383096000 | C113: 1.01 | D113: 130479000 | F113: 2182830000 | G113: 7488000 | H113: 200266000 | I113: 4.904159e+09
A114: 0001104659-26-028106 | B114: 5270578000 | C114: 5.92 | D114: 259697000 | F114: 4750731000 | G114: 59187000 | H114: 519847000 | I114: 1.086004e+10
A115: 0001104659-26-028308 | B115: 2659377000 | C115: 3.33 | D115: 134982000 | F115: 2375013000 | G115: 41614000 | H115: 284364000 | I115: 5.49535e+09
A116: 0001104659-26-028501 | B116: 11904077000 | C116: -1.88 | D116: 540989000 | F116: 10991490000 | G116: -155157000 | H116: 912587000 | I116: 2.4193986e+10
...

Sheet financials
A1: adsh | B1: tag | C1: version | D1: ddate | E1: qtrs | F1: uom | G1: segments | H1: coreg | I1: value
A2: 0000007789-26-000071 | B2: Liabilities | C2: us-gaap/2025 | D2: 20251231 | E2: 0 | F2: USD | I2: 40227249000
A3: 0000007789-26-000071 | B3: Assets | C3: us-gaap/2025 | D3: 20251231 | E3: 0 | F3: USD | I3: 45202596000
A4: 0000007789-26-000071 | B4: InterestAndDividendIncomeOperating | C4: us-gaap/2025 | D4: 20251231 | E4: 4 | F4: USD | I4: 2172756000
A5: 0000007789-26-000071 | B5: EarningsPerShareBasic | C5: us-gaap/2025 | D5: 20251231 | E5: 4 | F5: USD | I5: 2.79
A6: 0000022356-26-000069 | B6: NetIncomeLoss | C6: us-gaap/2025 | D6: 20251231 | E6: 4 | F6: USD | I6: 566251000
A7: 0000022356-26-000069 | B7: Assets | C7: us-gaap/2025 | D7: 20251231 | E7: 0 | F7: USD | I7: 32915089000
A8: 0000022356-26-000069 | B8: InterestAndDividendIncomeOperating | C8: us-gaap/2025 | D8: 20251231 | E8: 4 | F8: USD | I8: 1483723000
A9: 0000022356-26-000069 | B9: EarningsPerShareBasic | C9: us-gaap/2025 | D9: 20251231 | E9: 4 | F9: USD | I9: 4.04
A10: 0000034782-26-000011 | B10: EarningsPerShareBasic | C10: us-gaap/2025 | D10: 20251231 | E10: 4 | F10: USD | I10: 6.41
A11: 0000034782-26-000011 | B11: StockholdersEquity | C11: us-gaap/2025 | D11: 20251231 | E11: 0 | F11: USD | I11: 1274971000
A12: 0000035527-26-000124 | B12: InterestAndDividendIncomeOperating | C12: us-gaap/2025 | D12: 20251231 | E12: 4 | F12: USD | I12: 9903000000
A13: 0000036104-26-000011 | B13: EarningsPerShareBasic | C13: us-gaap/2025 | D13: 20251231 | E13: 4 | F13: USD | I13: 4.62
... A1520: 0002082866-26-000018 | B1520: NetIncomeLoss | C1520: us-gaap/2025 | D1520: 20251231 | E1520: 4 | F1520: USD | I1520: 641865000
